lesscode_test/__init__.py
lesscode_test/core/__init__.py
lesscode_test/core/cron_job.py
lesscode_test/core/handler.py
lesscode_test/core/job.py
lesscode_test/core/json_encoder.py
lesscode_test/core/parse_data.py
lesscode_test/core/request.py
lesscode_test/core/result.py
lesscode_test/core/task_handle.py
lesscode_test/core/task_info.py
lesscode_test/core/task_scheduler.py
lesscode_test-0.0.2.dist-info/METADATA
lesscode_test-0.0.2.dist-info/WHEEL
lesscode_test-0.0.2.dist-info/licenses/LICENSE
lesscode_test-0.0.2.dist-info/RECORD
