Metadata-Version: 2.1
Name: lesscode-test
Version: 0.0.2
Summary: Add your description here
Author-email: navysummer <navysummer@yeah.net>
License: MIT License
License-File: LICENSE
Classifier: License :: OSI Approved :: MIT License
Classifier: Operating System :: OS Independent
Classifier: Programming Language :: Python :: 3
Requires-Python: >=3.7
Requires-Dist: apscheduler>=3.9.1
Requires-Dist: gevent>=22.10.2
Requires-Dist: httpx>=0.24.1
Requires-Dist: lesscode-options>=0.0.0
Requires-Dist: pyyaml>=6.0.1
